setup.py
pusher/__init__.py
pusher/aiohttp.py
pusher/config.py
pusher/pusher.py
pusher/request.py
pusher/requests.py
pusher/sync.py
pusher/tornado.py
pusher/util.py
pusher_rest.egg-info/PKG-INFO
pusher_rest.egg-info/SOURCES.txt
pusher_rest.egg-info/dependency_links.txt
pusher_rest.egg-info/requires.txt
pusher_rest.egg-info/top_level.txt