Metadata-Version: 1.1
Name: pusher-rest
Version: 0.1.0
Summary: A Python library to interract with the Pusher API
Home-page: http://github.com/pusher/pusher-rest-python
Author: Pusher
Author-email: support@pusher.com
License: MIT
Keywords: pusher rest realtime websockets service
Platform: UNKNOWN
Classifier: License :: OSI Approved :: MIT License
Classifier: Programming Language :: Python
Classifier: Development Status :: 4 - Beta
Classifier: Intended Audience :: Developers
Classifier: Topic :: Internet :: WWW/HTTP
